sugar_spider/__init__.py
sugar_spider/common.py
sugar_spider/default.py
sugar_spider/fix.py
sugar_spider/model.py
sugar_spider/parser.py
sugar_spider/scripts.py
sugar_spider/util.py
sugar_spider/api/__init__.py
sugar_spider/api/app.py
sugar_spider/api/input_model.py
sugar_spider/explorer/__init__.py
sugar_spider/explorer/core.py
sugar_spider/explorer/util.py
sugar_spider/explorer/serpapi/__init__.py
sugar_spider/explorer/serpapi/google_search.py
sugar_spider/explorer/serpapi/google_shopping.py
sugar_spider/handler/__init__.py
sugar_spider/handler/exception.py
sugar_spider/handler/kafka.py
sugar_spider/handler/local.py
sugar_spider/manager/__init__.py
sugar_spider/manager/seatable.py
sugar_spider/metastore/__init__.py
sugar_spider/metastore/exception.py
sugar_spider/metastore/redis.py
sugar_spider/metastore/util.py
sugar_spider/scraper/__init__.py
sugar_spider/scraper/core.py
sugar_spider/scraper/brd/__init__.py
sugar_spider/scraper/brd/instagram.py
sugar_spider/scraper/brd/reddit.py
sugar_spider/scraper/brd/tiktok.py
sugar_spider/scraper/brd/youtube.py
sugar_spider/scraper/serpapi/__init__.py
sugar_spider/scraper/serpapi/google_product.py
sugar_spider-0.0.1.dist-info/METADATA
sugar_spider-0.0.1.dist-info/WHEEL
sugar_spider-0.0.1.dist-info/entry_points.txt
sugar_spider-0.0.1.dist-info/top_level.txt
sugar_spider-0.0.1.dist-info/RECORD
